securitytxt/__init__.py
securitytxt/securitytxt.py
securitytxt/parsers/__init__.py
securitytxt/parsers/file_parser.py
securitytxt/parsers/url_parser.py
securitytxt/parsers/textparsers/__init__.py
securitytxt/parsers/textparsers/comment_line_parser.py
securitytxt/parsers/textparsers/field_line_parser.py
securitytxt/parsers/textparsers/signed_text_parser.py
tests/__init__.py
tests/test_expired.py
tests/test_from_file.py
tests/test_from_url.py
wellknown_securitytxt-0.9.8.dist-info/LICENSE
wellknown_securitytxt-0.9.8.dist-info/METADATA
wellknown_securitytxt-0.9.8.dist-info/WHEEL
wellknown_securitytxt-0.9.8.dist-info/top_level.txt
wellknown_securitytxt-0.9.8.dist-info/RECORD
