Metadata-Version: 2.1
Name: wellknown-securitytxt
Version: 0.9.8
Summary: A package for finding and parsing security.txt files
Home-page: https://github.com/fwesters/securitytxt
Author: fwesters
License: UNKNOWN
Project-URL: Source, https://github.com/fwesters/securitytxt
Project-URL: Bug Tracker, https://github.com/fwesters/securitytxt/issues
Platform: UNKNOWN
Classifier: Development Status :: 4 - Beta
Classifier: License :: OSI Approved :: Apache Software License
Classifier: Operating System :: OS Independent
Classifier: Programming Language :: Python :: 3
Requires-Python: >=3.6
License-File: LICENSE
Requires-Dist: requests
Requires-Dist: python-dateutil
